{
    "startLocation": 1,
    "maps": [
        {
            "uid": 1,
            "image": "resources/maps/Kirchenraum.jpg",
          "mapSpots": [
            {
              "mapPosX": 30,
              "mapPosY": 15,
              "uid": 1
            },
            {
              "mapPosX": 75,
              "mapPosY": 110,
              "uid": 3
            }
          ]
        },
        {
          "uid": 2,
          "image": "resources/maps/Krypta.jpg",
          "mapSpots": [
            {
              "mapPosX": 20,
              "mapPosY": 15,
              "uid": 1
            },
            {
              "mapPosX": 50,
              "mapPosY": 70,
              "uid": 3
            }
          ]
        }
    ],
    "locations": [
        {
            "hotspots": [
                {
                    "images": [],
                    "posX": 195,
                    "posY": 0,
                    "posZ": 0,
                    "text": "some <a href=\"#\">nice!!! content</a>",
                    "audio": "resources/musi/highway.mp3",
                    "uid": 1,
                    "tooltip": "some historical stuff"
                },
                {
                    "images": [],
                    "posX": -3,
                    "posY": 29,
                    "posZ": -192,
                    "text": "some <a href=\"#\">super nice content</a>",
                    "audio": "resources/musi/highway.mp3",
                    "uid": 2,
                    "tooltip": "some other historical stuff"
                }
            ],
            "image": [
                "resources/panos/kirche001.jpg"
            ],
            "mapUid": 1,
            "startingView": [
                {
                    "comingFrom": 11,
                    "panAngle": 199,
                    "tiltAngle": 2
                }
            ],
            "transitions": [
                {
                    "posX": 80,
                    "posY": 150,
                    "posZ": 1,
                    "target_location": 3,
                    "tooltip": "Location 3"
                }
            ],
            "uid": 1
        },
        {
            "hotspots": [
                {
                    "images": [],
                    "posX": 80,
                    "posY": 50,
                    "posZ": 1,
                    "text": "some more <a href=\"#\">nice!!! content</a>",
                    "audio": "resources/musi/highway.mp3",
                    "uid": 1,
                    "tooltip": "awesome inscription"
                }
            ],
            "image": [
                "resources/panos/kirche003.jpg"
            ],
            "mapUid": 2,
            "startingView": [
                {
                    "comingFrom": 11,
                    "panAngle": 199,
                    "tiltAngle": 2
                }
            ],
            "transitions": [
                {
                    "posX": 0,
                    "posY": 150,
                    "posZ": 1,
                    "target_location": 1,
                    "tooltip": "Location 1"
                }
            ],
            "uid": 3
        }
    ]
}
